karabo/__init__.py
karabo/_version.py
karabo/version.py
karabo/bound/__init__.py
karabo/bound/configurator.py
karabo/bound/decorators.py
karabo/bound/device.py
karabo/bound/device_client.py
karabo/bound/device_server.py
karabo/bound/plugin_loader.py
karabo/bound/runner.py
karabo/bound/worker.py
karabo/bound/testing/__init__.py
karabo/bound/testing/eventloop.py
karabo/bound/testing/server_context.py
karabo/bound/testing/utils.py
karabo/bound/tests/__init__.py
karabo/bound/tests/api_module_test.py
karabo/bound/tests/boundDevice.py
karabo/bound/tests/brokenBoundDevice.py
karabo/bound/tests/configuration_example_classes.py
karabo/bound/tests/context_test.py
karabo/bound/tests/decorators_test.py
karabo/bound/tests/hash_test.py
karabo/bound/tests/hashfilter_test.py
karabo/bound/tests/imagedata_test.py
karabo/bound/tests/io_test.py
karabo/bound/tests/metadata_test.py
karabo/bound/tests/pluginloader_test.py
karabo/bound/tests/runner_test.py
karabo/bound/tests/schema_adler_test.py
karabo/bound/tests/schema_test.py
karabo/bound/tests/serializer_test.py
karabo/bound/tests/signal_slotable_test.py
karabo/bound/tests/timestamp_test.py
karabo/bound/tests/worker_test.py
karabo/bound/tests/binding/__init__.py
karabo/bound/tests/binding/test_attributes.py
karabo/bound/tests/binding/test_eventloop.py
karabo/bound/tests/binding/test_hash.py
karabo/bound/tests/binding/test_hash_attributes.py
karabo/bound/tests/binding/test_hash_attributes_node.py
karabo/bound/tests/binding/test_hash_node.py
karabo/bound/tests/binding/test_hashfilter.py
karabo/bound/tests/binding/test_imagedata.py
karabo/bound/tests/binding/test_json_parsing_for_init_string.py
karabo/bound/tests/binding/test_karabo_io.py
karabo/bound/tests/binding/test_logging_api.py
karabo/bound/tests/binding/test_ndarray_io.py
karabo/bound/tests/binding/test_pipeline_api.py
karabo/bound/tests/binding/test_pipeline_utils.py
karabo/bound/tests/binding/test_schema_api.py
karabo/bound/tests/binding/test_schema_elements.py
karabo_bound-3.0.8.dist-info/licenses/LICENSE.md
karabo_bound-3.0.8.dist-info/METADATA
karabo_bound-3.0.8.dist-info/WHEEL
karabo_bound-3.0.8.dist-info/entry_points.txt
karabo_bound-3.0.8.dist-info/top_level.txt
karabo_bound-3.0.8.dist-info/RECORD
