Metadata-Version: 2.4
Name: karabo.bound
Version: 3.0.8
Summary: Karabo's Bound Python API
Author-email: European XFEL GmbH <opensource@xfel.eu>
Maintainer-email: "S. Hauf" <steffen.hauf@xfel.eu>, "D. Goeries" <dennis.goeries@xfel.eu>
License-Expression: MPL-2.0
Project-URL: Homepage, https://github.com/European-XFEL/Karabo
Project-URL: Bug Reports, https://github.com/European-XFEL/Karabo/issues
Project-URL: Source, https://github.com/European-XFEL/Karabo
Keywords: Karabo,SCADA,async,control system
Classifier: Development Status :: 5 - Production/Stable
Classifier: Intended Audience :: Developers
Classifier: Intended Audience :: Science/Research
Requires-Python: >=3.12
License-File: LICENSE.md
Requires-Dist: aiomysql==0.2.0
Requires-Dist: aiosqlite==0.21.0
Requires-Dist: common==0.1.2
Requires-Dist: karabo-cpp==3.0.8
Requires-Dist: karabo-native==3.0.8
Requires-Dist: numpy==2.1.3
Requires-Dist: pytest==8.3.3
Dynamic: license-file
